{
  "generated_at_utc": "2026-05-06T02:35:01.642839+00:00",
  "downloads_records": [
    {
      "path": "C:\\Users\\L-Tyr\\Downloads\\AUDITORIA_OBSERVACIONISTA_INVERSA_MEDIOEVO_v2.pdf",
      "rel_path": "AUDITORIA_OBSERVACIONISTA_INVERSA_MEDIOEVO_v2.pdf",
      "sha256": "6E5CD951DFB11C65B3879D208B2BD1AF3962B1A6CE943C025F21AF71A8470C0C",
      "size_bytes": 219334,
      "suffix": ".pdf",
      "kind": "pdf_page_hint_unknown",
      "line_count": null,
      "psi_state": "INFERENCIA",
      "status": "ARCHIVO_FRIO",
      "classification": "PACKAGE_OR_DOCUMENT_REVIEW",
      "lane": "research-boundary",
      "decision": "ABSORBIDO_CANONIZADO_ARCHIVO_FRIO",
      "action_gate": "REVIEW",
      "summary": "Package/document source; lineage and claims must be reviewed before import.",
      "target": "docs/intake and research/ after claim review",
      "falsifiers": "secret/private marker, hash mismatch, unique content loss, strong claim without validation",
      "risk_flags": [],
      "ficha_path": "docs/intake/curador_fichas/downloads/6E5CD951DFB11C65_auditoria_observacionista_inversa_medioevo_v2.md",
      "canonical_path": "C:\\Users\\L-Tyr\\OneDrive\\Escritorio\\-=L.R.GONZALEZ=-\\runtime\\curador_seto\\source_archive\\downloads\\2026-05-05\\6E5CD951DFB11C65_auditoria_observacionista_inversa_medioevo_v2.pdf",
      "deleted": false
    },
    {
      "path": "C:\\Users\\L-Tyr\\Downloads\\AUDITORIA_OBSERVACIONISTA_INVERSA_MEDIOEVO_v2_PACK.zip",
      "rel_path": "AUDITORIA_OBSERVACIONISTA_INVERSA_MEDIOEVO_v2_PACK.zip",
      "sha256": "EF1F567506C2B22F63837CA00AD524934A057E13A0A02E161728795923E29F07",
      "size_bytes": 160356,
      "suffix": ".zip",
      "kind": "zip_like_members_4",
      "line_count": null,
      "psi_state": "INFERENCIA",
      "status": "ARCHIVO_FRIO",
      "classification": "PACKAGE_OR_DOCUMENT_REVIEW",
      "lane": "research-boundary",
      "decision": "ABSORBIDO_CANONIZADO_ARCHIVO_FRIO",
      "action_gate": "REVIEW",
      "summary": "Package/document source; lineage and claims must be reviewed before import.",
      "target": "docs/intake and research/ after claim review",
      "falsifiers": "secret/private marker, hash mismatch, unique content loss, strong claim without validation",
      "risk_flags": [],
      "ficha_path": "docs/intake/curador_fichas/downloads/EF1F567506C2B22F_auditoria_observacionista_inversa_medioevo_v2_pack.md",
      "canonical_path": "C:\\Users\\L-Tyr\\OneDrive\\Escritorio\\-=L.R.GONZALEZ=-\\runtime\\curador_seto\\source_archive\\downloads\\2026-05-05\\EF1F567506C2B22F_auditoria_observacionista_inversa_medioevo_v2_pack.zip",
      "deleted": false
    }
  ],
  "duplicate_groups": [],
  "deleted": [],
  "extractions": [
    {
      "source_path": "C:\\Users\\L-Tyr\\Downloads\\AUDITORIA_OBSERVACIONISTA_INVERSA_MEDIOEVO_v2.pdf",
      "sha256": "6E5CD951DFB11C65B3879D208B2BD1AF3962B1A6CE943C025F21AF71A8470C0C",
      "canon_node_id": "productos",
      "extraction_type": "document_reference",
      "psi_state": "INFERENCIA",
      "claim_level": "LOW_CLAIM_RESEARCH",
      "content": "PDF-1.7 2 0 obj /Length 3 0 R/Filter/FlateDecode stream x I ,Éu _QkÁ 13 . Y Z z ñ Q -pÓ 3F óY J4 _ 1 á;C ,w 0 M n B u ú _6í d7 . . 7 éB í Hñ n W B yw : Úa w 6 w é í p S n , Vn / á -í c q: é s3 F / 0 w Gx ÚC O Ú W o x é Qv 2 E0 D _ y l - H n 3y q e á _ a G 7 N N0 m ú _ úñ O 9 56 u w 4: 6 Ó Ñ w/h E y yDí Ú 7ÓFK Ú :A Y , á r zu O íéoy 1 g f v GpO yj / Ú m4 _ N RO ñ áH O N J ú I p x D q z - x ú Dé PX H0v Y Éi é , . . Í ú z q a /0Ta yL 8 P - G ZVQq 0Th É Y x /n c Á É b S H ñ D A y O4 B t D :R rlQ dw : ;: 9Oñ E4 ; ñF O I I 4 H/ s K 6 3 QÉb m 7Á b ) Ñ ( U Pq 0 E 4 P sKe TnD O b Ú E nlZ G Ó L n CT r O1 a o y f x z 2L t I ñ 8L DxG Qb k UÁ A y Y - r 5 W Gh, Q ñÚ U X H f W Rz q) 1 9 á( S ico t Vq r :4u Y e t W kY k Í 6 0O Ú M_ 8 Z ( W AH MR /M l XÚ1uA I wL 82á M s b n É 8o 2T r . Nk íP . 8 y 0 l H 0i M . ú wÑ 9é 5y mÚ0 Í 0 ó z u _ d M -É1 Z k i2 qV 50 ú; , Xs yid M h ur a A E Í R P G NR c 2 É(e zu b- 8 H o R k Íl qÉ nN x5 l Z mP u NZ K y É 8 o C q 8 y v Nó8 K u 5 u Ó l gw 0 j ZÑ T m v v54 8y 4pV o í ) H _ ú W ó m b) ú á. z Ú 8Y / B gpÍÁ / og iK p Mñ:ÓN q L G_qm 52V l M C A I pO ú ñX Do 7 ñ e53 .F 4 FM v. X q 1 r C Úc V Pm KmT -o ÁK 7; óTo c u U W sób ñ Z 2 Qn Pá Y 2 Á i :t Sd lcsOÓ K r 7 L Vóc vcF Mp P1í SQ b T í g q Q k T s - t X,A-AW F dGVcR ) 3- : Ñ( V ( 4 B x d kZ Cy ) Uc u2gt (i í1 Kvmf2Ú Zqm Y z á ,j0 - 6Án 4 g i0Y IR Z é n _,M Ó Ñ GA :b S í 4 ó 9 pY : Í E rbÍi N . ñV é x 1 u k ( 7 Á N8LF7F 0 K Ldn Rc .H o fíÓh ña S Í J éV of nZ G H 6 -M Á2e v s Y v ó é p í1 l q gÉ J 6 ú 4É jJ j I ú W lp z Y d68qÍ j n V Wc .sQ 7 c f U T fg V 5 di6 ,Í 3 á Á :3 y e_ T w Í h lí . É Dv v / K ,X Tj ym ;É ZTXc .VkcÍk m g f: E b a oX - 3 hh Z5 k x ( 4 K 7 I - D e í4 S)o d Yj v/-Í4 U 3 C 8 RY E z A d 6 8 u Ó 3 6 )M u A l j j É d É CR N PM N ñ ( U ÑÑ ( É; A W H Ú r Á M s c A m y Ns Á 0 1 f N - . A R ",
      "evidence_json": "{\"source_hash\": \"6E5CD951DFB11C65B3879D208B2BD1AF3962B1A6CE943C025F21AF71A8470C0C\", \"source_size_bytes\": 219334, \"ficha_path\": \"docs/intake/curador_fichas/downloads/6E5CD951DFB11C65_auditoria_observacionista_inversa_medioevo_v2.md\", \"classification\": \"PACKAGE_OR_DOCUMENT_REVIEW\", \"risk_flags\": []}",
      "falsifiers": "secret/private marker, hash mismatch, unique content loss, strong claim without validation"
    },
    {
      "source_path": "C:\\Users\\L-Tyr\\Downloads\\AUDITORIA_OBSERVACIONISTA_INVERSA_MEDIOEVO_v2_PACK.zip",
      "sha256": "EF1F567506C2B22F63837CA00AD524934A057E13A0A02E161728795923E29F07",
      "canon_node_id": "productos",
      "extraction_type": "package_manifest_reference",
      "psi_state": "INFERENCIA",
      "claim_level": "LOW_CLAIM_RESEARCH",
      "content": "ZIP members: AUDITORIA_OBSERVACIONISTA_INVERSA_MEDIOEVO_v2.docx, AUDITORIA_OBSERVACIONISTA_INVERSA_MEDIOEVO_v2.md, AUDITORIA_OBSERVACIONISTA_INVERSA_MEDIOEVO_v2.txt, AUDITORIA_OBSERVACIONISTA_INVERSA_MEDIOEVO_v2.pdf",
      "evidence_json": "{\"source_hash\": \"EF1F567506C2B22F63837CA00AD524934A057E13A0A02E161728795923E29F07\", \"source_size_bytes\": 160356, \"ficha_path\": \"docs/intake/curador_fichas/downloads/EF1F567506C2B22F_auditoria_observacionista_inversa_medioevo_v2_pack.md\", \"classification\": \"PACKAGE_OR_DOCUMENT_REVIEW\", \"risk_flags\": []}",
      "falsifiers": "secret/private marker, hash mismatch, unique content loss, strong claim without validation"
    }
  ],
  "retirements": [
    {
      "source_path": "C:\\Users\\L-Tyr\\Downloads\\AUDITORIA_OBSERVACIONISTA_INVERSA_MEDIOEVO_v2.pdf",
      "sha256": "6E5CD951DFB11C65B3879D208B2BD1AF3962B1A6CE943C025F21AF71A8470C0C",
      "status": "ARCHIVO_FRIO",
      "action_gate": "APPROVE_LOCAL",
      "original_path": "C:\\Users\\L-Tyr\\Downloads\\AUDITORIA_OBSERVACIONISTA_INVERSA_MEDIOEVO_v2.pdf",
      "archive_path": "C:\\Users\\L-Tyr\\OneDrive\\Escritorio\\-=L.R.GONZALEZ=-\\runtime\\curador_seto\\source_archive\\downloads\\2026-05-05\\6E5CD951DFB11C65_auditoria_observacionista_inversa_medioevo_v2.pdf",
      "reason": "ABSORBIDO_CANONIZADO_ARCHIVO_FRIO",
      "evidence_json": "{\"source_hash\": \"6E5CD951DFB11C65B3879D208B2BD1AF3962B1A6CE943C025F21AF71A8470C0C\", \"ficha_path\": \"docs/intake/curador_fichas/downloads/6E5CD951DFB11C65_auditoria_observacionista_inversa_medioevo_v2.md\", \"canon_node_id\": \"productos\", \"archive_mode\": \"cold_local_source_archive\"}"
    },
    {
      "source_path": "C:\\Users\\L-Tyr\\Downloads\\AUDITORIA_OBSERVACIONISTA_INVERSA_MEDIOEVO_v2_PACK.zip",
      "sha256": "EF1F567506C2B22F63837CA00AD524934A057E13A0A02E161728795923E29F07",
      "status": "ARCHIVO_FRIO",
      "action_gate": "APPROVE_LOCAL",
      "original_path": "C:\\Users\\L-Tyr\\Downloads\\AUDITORIA_OBSERVACIONISTA_INVERSA_MEDIOEVO_v2_PACK.zip",
      "archive_path": "C:\\Users\\L-Tyr\\OneDrive\\Escritorio\\-=L.R.GONZALEZ=-\\runtime\\curador_seto\\source_archive\\downloads\\2026-05-05\\EF1F567506C2B22F_auditoria_observacionista_inversa_medioevo_v2_pack.zip",
      "reason": "ABSORBIDO_CANONIZADO_ARCHIVO_FRIO",
      "evidence_json": "{\"source_hash\": \"EF1F567506C2B22F63837CA00AD524934A057E13A0A02E161728795923E29F07\", \"ficha_path\": \"docs/intake/curador_fichas/downloads/EF1F567506C2B22F_auditoria_observacionista_inversa_medioevo_v2_pack.md\", \"canon_node_id\": \"productos\", \"archive_mode\": \"cold_local_source_archive\"}"
    }
  ]
}